Workbook

Sheet Assumptions
A1: Syria Silicon — Staged Development Project (USD 105M) — Financial Model V6
A2: Basis date: 5 July 2026. Supersedes the V4/V5 thread. Inputs in blue; key open items in yellow.
A4: PRICES (USD/t, FOB basis)
A5: Washed industrial silica — base price | B5: 40 | C5: USD/t | D5: Source: B. Maluish, MD VRX Silica (ASX:VRX), project correspondence — range 35–45
A6: Glass-grade blended price — derived from product mix below (replaces unsupported $180/t)
A7: Container-glass share | B7: 0.4 | C7: share
A8: Container-glass price | B8: 52 | C8: USD/t | D8: Maluish glass band upper + regional delivery premium
A9: Solar-glass share | B9: 0.3 | C9: share
A10: Solar-glass price | B10: 55 | C10: USD/t | D10: Maluish 4N solar glass 50–60
A11: Foundry/specialty share | B11: 0.3 | C11: share
A12: Foundry/specialty price | B12: 85 | C12: USD/t | D12: Market Study high-purity band 40–120
A13: Glass-grade blended price (derived) | B13: =B7*B8+B9*B10+B11*B12 -> 62.8 | C13: USD/t
A14: HPQ indicative (Stage 3 upside only — excluded from base returns) | B14: 600 | C14: USD/t | D14: Subject to metallurgical confirmation
A15: Price multiplier (scenario lever) | B15: 1 | C15: x
A16: COSTS (USD/t unless noted)
A17: Mining (self-managed) | B17: 4 | C17: USD/t | D17: V4 bottom-up; June 2026 decision to self-manage extraction
A18: Haulage mine to Hassia (~100 km) | B18: 5 | C18: USD/t | D18: V4 bottom-up
A19: Wash-plant processing | B19: 5 | C19: USD/t | D19: V4 bottom-up
A20: Site overhead | B20: 2.5 | C20: USD/t | D20: V4 bottom-up
A21: Washed cash cost ex-royalty | B21: =SUM(B17:B20) -> 16.5 | C21: USD/t
A22: Upgrade adder (acid leach + magnetic separation) | B22: 14 | C22: USD/t | D22: Pending Stage 2 vendor quotes — key open item
A23: Royalty — ad-valorem on realised price | B23: 0.03 | C23: rate | D23: June 2026 decision (Saudi/Turkish benchmark); enacted basis pending legal confirmation
A24: SG&A — Stage 1 (Years 1–3) | B24: 2 | C24: USD M/yr | D24: Estimate
A25: SG&A — from Stage 2 (Year 4+, ~1 Mtpa operation) | B25: 4 | C25: USD M/yr | D25: Estimate
A26: Sustaining capex (% of cumulative expansion capex) | B26: 0.02 | C26: per yr | D26: Estimate
A27: Volume multiplier (scenario lever) | B27: 1 | C27: x
A28: CAPITAL (USD M) — commitment envelopes incl. contingency and working capital (see Bridge sheet)
A29: Stage 1 envelope | B29: 25 | C29: USD M | D29: Public pathway figure
A30: Stage 1 spend — Year 0 | B30: 15 | C30: USD M
A31: Stage 1 spend — Year 1 | B31: 10 | C31: USD M
A32: Stage 2 envelope | B32: 25 | C32: USD M
A33: Stage 2 spend — Year 3 | B33: 10 | C33: USD M
A34: Stage 2 spend — Year 4 | B34: 15 | C34: USD M
A35: Depreciation life (straight line) | B35: 10 | C35: years
A36: TAX, WORKING CAPITAL, DISCOUNTING
A37: Corporate tax rate (on profit) | B37: 0.1 | C37: rate | D37: 2026 Syrian industrial rate — pending legal confirmation as enacted law
A38: Working capital (% of revenue) | B38: 0.1 | C38: rate | D38: Estimate
A39: Discount rate (real, ungeared) | B39: 0.1 | C39: rate | D39: Base
A41: Funding: 100% equity base case (no external collateral, so conventional secured debt is unavailable at outset — June 2026 analysis). Equipment leasing, offtaker advances, and royalty/streaming are later dilution-reduction levers.
A42: Stage 1 plant capacity (kt/yr) | B42: 450 | C42: kt

Sheet Model
A1: Integrated Model — Years 0–10 (USD M unless noted)
B2: Year 0 | C2: Year 1 | D2: Year 2 | E2: Year 3 | F2: Year 4 | G2: Year 5 | H2: Year 6 | I2: Year 7 | J2: Year 8 | K2: Year 9 | L2: Year 10
A3: (year index) | B3: 0 | C3: 1 | D3: 2 | E3: 3 | F3: 4 | G3: 5 | H3: 6 | I3: 7 | J3: 8 | K3: 9 | L3: 10
A5: Base production plan (kt) | B5: 0 | C5: 150 | D5: 300 | E5: 400 | F5: 650 | G5: 800 | H5: 1000 | I5: 1000 | J5: 1000 | K5: 1000 | L5: 1000
A6: Production (kt, after volume multiplier) | B6: =B5*Assumptions!$B$27 -> 0 | C6: =C5*Assumptions!$B$27 -> 150 | D6: =D5*Assumptions!$B$27 -> 300 | E6: =E5*Assumptions!$B$27 -> 400 | F6: =F5*Assumptions!$B$27 -> 650 | G6: =G5*Assumptions!$B$27 -> 800 | H6: =H5*Assumptions!$B$27 -> 1000 | I6: =I5*Assumptions!$B$27 -> 1000 | ... L6: =L5*Assumptions!$B$27 -> 1000
A7: Upgraded share | B7: 0 | C7: 0 | D7: 0 | E7: 0 | F7: 0.25 | G7: 0.35 | H7: 0.4 | I7: 0.4 | J7: 0.4 | K7: 0.4 | L7: 0.4
A8: Upgraded volume (kt) | B8: =B6*B7 -> 0 | C8: =C6*C7 -> 0 | D8: =D6*D7 -> 0 | E8: =E6*E7 -> 0 | F8: =F6*F7 -> 162.5 | G8: =G6*G7 -> 280 | H8: =H6*H7 -> 400 | I8: =I6*I7 -> 400 | ... L8: =L6*L7 -> 400
A9: Washed volume (kt) | B9: =B6-B8 -> 0 | C9: =C6-C8 -> 150 | D9: =D6-D8 -> 300 | E9: =E6-E8 -> 400 | F9: =F6-F8 -> 487.5 | G9: =G6-G8 -> 520 | H9: =H6-H8 -> 600 | I9: =I6-I8 -> 600 | ... L9: =L6-L8 -> 600
A11: Washed price (USD/t) | B11: =Assumptions!$B$5*Assumptions!$B$15 -> 40 | C11: =Assumptions!$B$5*Assumptions!$B$15 -> 40 | D11: =Assumptions!$B$5*Assumptions!$B$15 -> 40 | E11: =Assumptions!$B$5*Assumptions!$B$15 -> 40 | F11: =Assumptions!$B$5*Assumptions!$B$15 -> 40 | G11: =Assumptions!$B$5*Assumptions!$B$15 -> 40 | H11: =Assumptions!$B$5*Assumptions!$B$15 -> 40 | I11: =Assumptions!$B$5*Assumptions!$B$15 -> 40 | ... L11: =Assumptions!$B$5*Assumptions!$B$15 -> 40
A12: Glass-grade price (USD/t) | B12: =Assumptions!$B$13*Assumptions!$B$15 -> 62.8 | C12: =Assumptions!$B$13*Assumptions!$B$15 -> 62.8 | D12: =Assumptions!$B$13*Assumptions!$B$15 -> 62.8 | E12: =Assumptions!$B$13*Assumptions!$B$15 -> 62.8 | F12: =Assumptions!$B$13*Assumptions!$B$15 -> 62.8 | G12: =Assumptions!$B$13*Assumptions!$B$15 -> 62.8 | H12: =Assumptions!$B$13*Assumptions!$B$15 -> 62.8 | I12: =Assumptions!$B$13*Assumptions!$B$15 -> 62.8 | ... L12: =Assumptions!$B$13*Assumptions!$B$15 -> 62.8
A14: Revenue — washed | B14: =B9*B11/1000 -> 0 | C14: =C9*C11/1000 -> 6 | D14: =D9*D11/1000 -> 12 | E14: =E9*E11/1000 -> 16 | F14: =F9*F11/1000 -> 19.5 | G14: =G9*G11/1000 -> 20.8 | H14: =H9*H11/1000 -> 24 | I14: =I9*I11/1000 -> 24 | ... L14: =L9*L11/1000 -> 24
A15: Revenue — glass-grade | B15: =B8*B12/1000 -> 0 | C15: =C8*C12/1000 -> 0 | D15: =D8*D12/1000 -> 0 | E15: =E8*E12/1000 -> 0 | F15: =F8*F12/1000 -> 10.205 | G15: =G8*G12/1000 -> 17.584 | H15: =H8*H12/1000 -> 25.12 | I15: =I8*I12/1000 -> 25.12 | ... L15: =L8*L12/1000 -> 25.12
A16: Total revenue | B16: =B14+B15 -> 0 | C16: =C14+C15 -> 6 | D16: =D14+D15 -> 12 | E16: =E14+E15 -> 16 | F16: =F14+F15 -> 29.705 | G16: =G14+G15 -> 38.384 | H16: =H14+H15 -> 49.12 | I16: =I14+I15 -> 49.12 | ... L16: =L14+L15 -> 49.12
A17: Royalty (ad-valorem) | B17: =B16*Assumptions!$B$23 -> 0 | C17: =C16*Assumptions!$B$23 -> 0.18 | D17: =D16*Assumptions!$B$23 -> 0.36 | E17: =E16*Assumptions!$B$23 -> 0.48 | F17: =F16*Assumptions!$B$23 -> 0.89115 | G17: =G16*Assumptions!$B$23 -> 1.15152 | H17: =H16*Assumptions!$B$23 -> 1.4736 | I17: =I16*Assumptions!$B$23 -> 1.4736 | ... L17: =L16*Assumptions!$B$23 -> 1.4736
A18: Cash costs — washed | B18: =B9*Assumptions!$B$21/1000 -> 0 | C18: =C9*Assumptions!$B$21/1000 -> 2.475 | D18: =D9*Assumptions!$B$21/1000 -> 4.95 | E18: =E9*Assumptions!$B$21/1000 -> 6.6 | F18: =F9*Assumptions!$B$21/1000 -> 8.04375 | G18: =G9*Assumptions!$B$21/1000 -> 8.58 | H18: =H9*Assumptions!$B$21/1000 -> 9.9 | I18: =I9*Assumptions!$B$21/1000 -> 9.9 | ... L18: =L9*Assumptions!$B$21/1000 -> 9.9
A19: Cash costs — glass-grade | B19: =B8*(Assumptions!$B$21+Assumptions!$B$22)/1000 -> 0 | C19: =C8*(Assumptions!$B$21+Assumptions!$B$22)/1000 -> 0 | D19: =D8*(Assumptions!$B$21+Assumptions!$B$22)/1000 -> 0 | E19: =E8*(Assumptions!$B$21+Assumptions!$B$22)/1000 -> 0 | F19: =F8*(Assumptions!$B$21+Assumptions!$B$22)/1000 -> 4.95625 | G19: =G8*(Assumptions!$B$21+Assumptions!$B$22)/1000 -> 8.54 | H19: =H8*(Assumptions!$B$21+Assumptions!$B$22)/1000 -> 12.2 | I19: =I8*(Assumptions!$B$21+Assumptions!$B$22)/1000 -> 12.2 | ... L19: =L8*(Assumptions!$B$21+Assumptions!$B$22)/1000 -> 12.2
A20: SG&A | B20: =IF(B3=0,0,IF(B3<=3,Assumptions!$B$24,Assumptions!$B$25)) -> 0 | C20: =IF(C3=0,0,IF(C3<=3,Assumptions!$B$24,Assumptions!$B$25)) -> 2 | D20: =IF(D3=0,0,IF(D3<=3,Assumptions!$B$24,Assumptions!$B$25)) -> 2 | E20: =IF(E3=0,0,IF(E3<=3,Assumptions!$B$24,Assumptions!$B$25)) -> 2 | F20: =IF(F3=0,0,IF(F3<=3,Assumptions!$B$24,Assumptions!$B$25)) -> 4 | G20: =IF(G3=0,0,IF(G3<=3,Assumptions!$B$24,Assumptions!$B$25)) -> 4 | H20: =IF(H3=0,0,IF(H3<=3,Assumptions!$B$24,Assumptions!$B$25)) -> 4 | I20: =IF(I3=0,0,IF(I3<=3,Assumptions!$B$24,Assumptions!$B$25)) -> 4 | ... L20: =IF(L3=0,0,IF(L3<=3,Assumptions!$B$24,Assumptions!$B$25)) -> 4
A21: EBITDA | B21: =B16-B17-B18-B19-B20 -> 0 | C21: =C16-C17-C18-C19-C20 -> 1.345 | D21: =D16-D17-D18-D19-D20 -> 4.69 | E21: =E16-E17-E18-E19-E20 -> 6.92 | F21: =F16-F17-F18-F19-F20 -> 11.81385 | G21: =G16-G17-G18-G19-G20 -> 16.11248 | H21: =H16-H17-H18-H19-H20 -> 21.5464 | I21: =I16-I17-I18-I19-I20 -> 21.5464 | ... L21: =L16-L17-L18-L19-L20 -> 21.5464
A23: Expansion capex | B23: 15 | C23: 10 | D23: 0 | E23: 10 | F23: 15 | G23: 0 | H23: 0 | I23: 0 | J23: 0 | K23: 0 | L23: 0
A24: Sustaining capex | B24: =IF(B3>=2,Assumptions!$B$26*SUM($B$23:B23),0) -> 0 | C24: =IF(C3>=2,Assumptions!$B$26*SUM($B$23:C23),0) -> 0 | D24: =IF(D3>=2,Assumptions!$B$26*SUM($B$23:D23),0) -> 0.5 | E24: =IF(E3>=2,Assumptions!$B$26*SUM($B$23:E23),0) -> 0.7 | F24: =IF(F3>=2,Assumptions!$B$26*SUM($B$23:F23),0) -> 1 | G24: =IF(G3>=2,Assumptions!$B$26*SUM($B$23:G23),0) -> 1 | H24: =IF(H3>=2,Assumptions!$B$26*SUM($B$23:H23),0) -> 1 | I24: =IF(I3>=2,Assumptions!$B$26*SUM($B$23:I23),0) -> 1 | ... L24: =IF(L3>=2,Assumptions!$B$26*SUM($B$23:L23),0) -> 1
A25: Total capex | B25: =B23+B24 -> 15 | C25: =C23+C24 -> 10 | D25: =D23+D24 -> 0.5 | E25: =E23+E24 -> 10.7 | F25: =F23+F24 -> 16 | G25: =G23+G24 -> 1 | H25: =H23+H24 -> 1 | I25: =I23+I24 -> 1 | ... L25: =L23+L24 -> 1
A26: Depreciation | B26: =IF(B3>=1,Assumptions!$B$29/Assumptions!$B$35,0)+IF(B3>=4,Assumptions!$B$32/Assumptions!$B$35,0) -> 0 | C26: =IF(C3>=1,Assumptions!$B$29/Assumptions!$B$35,0)+IF(C3>=4,Assumptions!$B$32/Assumptions!$B$35,0) -> 2.5 | D26: =IF(D3>=1,Assumptions!$B$29/Assumptions!$B$35,0)+IF(D3>=4,Assumptions!$B$32/Assumptions!$B$35,0) -> 2.5 | E26: =IF(E3>=1,Assumptions!$B$29/Assumptions!$B$35,0)+IF(E3>=4,Assumptions!$B$32/Assumptions!$B$35,0) -> 2.5 | F26: =IF(F3>=1,Assumptions!$B$29/Assumptions!$B$35,0)+IF(F3>=4,Assumptions!$B$32/Assumptions!$B$35,0) -> 5 | G26: =IF(G3>=1,Assumptions!$B$29/Assumptions!$B$35,0)+IF(G3>=4,Assumptions!$B$32/Assumptions!$B$35,0) -> 5 | H26: =IF(H3>=1,Assumptions!$B$29/Assumptions!$B$35,0)+IF(H3>=4,Assumptions!$B$32/Assumptions!$B$35,0) -> 5 | I26: =IF(I3>=1,Assumptions!$B$29/Assumptions!$B$35,0)+IF(I3>=4,Assumptions!$B$32/Assumptions!$B$35,0) -> 5 | ... L26: =IF(L3>=1,Assumptions!$B$29/Assumptions!$B$35,0)+IF(L3>=4,Assumptions!$B$32/Assumptions!$B$35,0) -> 5
A27: EBT | B27: =B21-B26 -> 0 | C27: =C21-C26 -> -1.155 | D27: =D21-D26 -> 2.19 | E27: =E21-E26 -> 4.42 | F27: =F21-F26 -> 6.81385 | G27: =G21-G26 -> 11.11248 | H27: =H21-H26 -> 16.5464 | I27: =I21-I26 -> 16.5464 | ... L27: =L21-L26 -> 16.5464
A28: Tax | B28: =MAX(0,B27*Assumptions!$B$37) -> 0 | C28: =MAX(0,C27*Assumptions!$B$37) -> 0 | D28: =MAX(0,D27*Assumptions!$B$37) -> 0.219 | E28: =MAX(0,E27*Assumptions!$B$37) -> 0.442 | F28: =MAX(0,F27*Assumptions!$B$37) -> 0.681385 | G28: =MAX(0,G27*Assumptions!$B$37) -> 1.111248 | H28: =MAX(0,H27*Assumptions!$B$37) -> 1.65464 | I28: =MAX(0,I27*Assumptions!$B$37) -> 1.65464 | ... L28: =MAX(0,L27*Assumptions!$B$37) -> 1.65464
A29: Net income | B29: =B27-B28 -> 0 | C29: =C27-C28 -> -1.155 | D29: =D27-D28 -> 1.971 | E29: =E27-E28 -> 3.978 | F29: =F27-F28 -> 6.132465 | G29: =G27-G28 -> 10.001232 | H29: =H27-H28 -> 14.89176 | I29: =I27-I28 -> 14.89176 | ... L29: =L27-L28 -> 14.89176
A31: Change in working capital | B31: =Assumptions!$B$38*B16 -> 0 | C31: =Assumptions!$B$38*(C16-B16) -> 0.6 | D31: =Assumptions!$B$38*(D16-C16) -> 0.6 | E31: =Assumptions!$B$38*(E16-D16) -> 0.4 | F31: =Assumptions!$B$38*(F16-E16) -> 1.3705 | G31: =Assumptions!$B$38*(G16-F16) -> 0.8679 | H31: =Assumptions!$B$38*(H16-G16) -> 1.0736 | I31: =Assumptions!$B$38*(I16-H16) -> 0 | J31: =Assumptions!$B$38*(J16-I16) -> 0 | ... L31: =Assumptions!$B$38*(L16-K16) -> 0
A32: Free cash flow (equity, ungeared) | B32: =B21-B28-B25-B31 -> -15 | C32: =C21-C28-C25-C31 -> -9.255 | D32: =D21-D28-D25-D31 -> 3.371 | E32: =E21-E28-E25-E31 -> -4.622 | F32: =F21-F28-F25-F31 -> -6.238035 | G32: =G21-G28-G25-G31 -> 13.133332 | H32: =H21-H28-H25-H31 -> 17.81816 | I32: =I21-I28-I25-I31 -> 18.89176 | ... L32: =L21-L28-L25-L31 -> 18.89176
A33: Cumulative FCF | B33: =B32 -> -15 | C33: =B33+C32 -> -24.255 | D33: =C33+D32 -> -20.884 | E33: =D33+E32 -> -25.506 | F33: =E33+F32 -> -31.744035 | G33: =F33+G32 -> -18.610703 | H33: =G33+H32 -> -0.792543 | I33: =H33+I32 -> 18.099217 | J33: =I33+J32 -> 36.990977 | ... L33: =K33+L32 -> 74.774497
A35: RETURNS — consolidated Stages 1+2
A36: NPV at discount rate (USD M) | B36: =B32+NPV(Assumptions!$B$39,C32:L32) -> 23.654875
A37: IRR (ungeared, 100% equity) | B37: =IRR(B32:L32) -> 0.21124849
A38: Years with negative cumulative FCF (payback indicator) | B38: =COUNTIF(B33:L33,"<0") -> 7
A40: STAGE 1 STANDALONE — washed product only, Stage 1 capex only (USD 25M single-stage view)
A41: Revenue (all washed) | B41: =MIN(B6,Assumptions!$B$42)*B11/1000 -> 0 | C41: =MIN(C6,Assumptions!$B$42)*C11/1000 -> 6 | D41: =MIN(D6,Assumptions!$B$42)*D11/1000 -> 12 | E41: =MIN(E6,Assumptions!$B$42)*E11/1000 -> 16 | F41: =MIN(F6,Assumptions!$B$42)*F11/1000 -> 18 | G41: =MIN(G6,Assumptions!$B$42)*G11/1000 -> 18 | H41: =MIN(H6,Assumptions!$B$42)*H11/1000 -> 18 | I41: =MIN(I6,Assumptions!$B$42)*I11/1000 -> 18 | ... L41: =MIN(L6,Assumptions!$B$42)*L11/1000 -> 18
A42: EBITDA | B42: =B41*(1-Assumptions!$B$23)-MIN(B6,Assumptions!$B$42)*Assumptions!$B$21/1000-IF(B3=0,0,Assumptions!$B$24) -> 0 | C42: =C41*(1-Assumptions!$B$23)-MIN(C6,Assumptions!$B$42)*Assumptions!$B$21/1000-IF(C3=0,0,Assumptions!$B$24) -> 1.345 | D42: =D41*(1-Assumptions!$B$23)-MIN(D6,Assumptions!$B$42)*Assumptions!$B$21/1000-IF(D3=0,0,Assumptions!$B$24) -> 4.69 | E42: =E41*(1-Assumptions!$B$23)-MIN(E6,Assumptions!$B$42)*Assumptions!$B$21/1000-IF(E3=0,0,Assumptions!$B$24) -> 6.92 | F42: =F41*(1-Assumptions!$B$23)-MIN(F6,Assumptions!$B$42)*Assumptions!$B$21/1000-IF(F3=0,0,Assumptions!$B$24) -> 8.035 | G42: =G41*(1-Assumptions!$B$23)-MIN(G6,Assumptions!$B$42)*Assumptions!$B$21/1000-IF(G3=0,0,Assumptions!$B$24) -> 8.035 | H42: =H41*(1-Assumptions!$B$23)-MIN(H6,Assumptions!$B$42)*Assumptions!$B$21/1000-IF(H3=0,0,Assumptions!$B$24) -> 8.035 | I42: =I41*(1-Assumptions!$B$23)-MIN(I6,Assumptions!$B$42)*Assumptions!$B$21/1000-IF(I3=0,0,Assumptions!$B$24) -> 8.035 | ... L42: =L41*(1-Assumptions!$B$23)-MIN(L6,Assumptions!$B$42)*Assumptions!$B$21/1000-IF(L3=0,0,Assumptions!$B$24) -> 8.035
A43: Tax (approx, on EBITDA less Stage 1 depreciation) | B43: =MAX(0,(B42-IF(B3>=1,Assumptions!$B$29/Assumptions!$B$35,0))*Assumptions!$B$37) -> 0 | C43: =MAX(0,(C42-IF(C3>=1,Assumptions!$B$29/Assumptions!$B$35,0))*Assumptions!$B$37) -> 0 | D43: =MAX(0,(D42-IF(D3>=1,Assumptions!$B$29/Assumptions!$B$35,0))*Assumptions!$B$37) -> 0.219 | E43: =MAX(0,(E42-IF(E3>=1,Assumptions!$B$29/Assumptions!$B$35,0))*Assumptions!$B$37) -> 0.442 | F43: =MAX(0,(F42-IF(F3>=1,Assumptions!$B$29/Assumptions!$B$35,0))*Assumptions!$B$37) -> 0.5535 | G43: =MAX(0,(G42-IF(G3>=1,Assumptions!$B$29/Assumptions!$B$35,0))*Assumptions!$B$37) -> 0.5535 | H43: =MAX(0,(H42-IF(H3>=1,Assumptions!$B$29/Assumptions!$B$35,0))*Assumptions!$B$37) -> 0.5535 | I43: =MAX(0,(I42-IF(I3>=1,Assumptions!$B$29/Assumptions!$B$35,0))*Assumptions!$B$37) -> 0.5535 | ... L43: =MAX(0,(L42-IF(L3>=1,Assumptions!$B$29/Assumptions!$B$35,0))*Assumptions!$B$37) -> 0.5535
A44: FCF | B44: =B42-B43-15-Assumptions!$B$38*B41 -> -15 | C44: =C42-C43-10-Assumptions!$B$38*(C41-B41) -> -9.255 | D44: =D42-D43-0-Assumptions!$B$38*(D41-C41) -> 3.871 | E44: =E42-E43-0-Assumptions!$B$38*(E41-D41) -> 6.078 | F44: =F42-F43-0-Assumptions!$B$38*(F41-E41) -> 7.2815 | G44: =G42-G43-0-Assumptions!$B$38*(G41-F41) -> 7.4815 | H44: =H42-H43-0-Assumptions!$B$38*(H41-G41) -> 7.4815 | I44: =I42-I43-0-Assumptions!$B$38*(I41-H41) -> 7.4815 | J44: =J42-J43-0-Assumptions!$B$38*(J41-I41) -> 7.4815 | K44: =K42-K43-0-Assumptions!$B$38*(K41-J41) -> 7.4815 | L44: =L42-L43-0-Assumptions!$B$38*(L41-K41) -> 7.4815
A45: Cumulative FCF | B45: =B44 -> -15 | C45: =B45+C44 -> -24.255 | D45: =C45+D44 -> -20.384 | E45: =D45+E44 -> -14.306 | F45: =E45+F44 -> -7.0245 | G45: =F45+G44 -> 0.457 | H45: =G45+H44 -> 7.9385 | I45: =H45+I44 -> 15.42 | J45: =I45+J44 -> 22.9015 | ... L45: =K45+L44 -> 37.8645
A46: Stage 1 IRR | B46: =IRR(B44:L44) -> 0.18910305
A47: Stage 1 NPV (USD M) | B47: =B44+NPV(Assumptions!$B$39,C44:L44) -> 11.580621

Sheet Sensitivity
A1: Plateau-year (Year 6) EBITDA sensitivity — USD M
A2: Analytic at the Year-6 plan (500 kt, 55% upgraded). Prices net of ad-valorem royalty. For full-model scenarios use the multiplier levers on Assumptions (B15, B27).
B4: Price multiplier | C4: 0.8 | D4: 0.9 | E4: 1 | F4: 1.1 | G4: 1.2
A5: Volume multiplier | B5: 0.75 | C5: =$B5*Model!$H$5*(Model!$H$7*(Assumptions!$B$13*C$4*(1-Assumptions!$B$23)-(Assumptions!$B$21+Assumptions!$B$22))+(1-Model!$H$7)*(Assumptions!$B$5*C$4*(1-Assumptions!$B$23)-Assumptions!$B$21))/1000-Assumptions!$B$25 -> 8.01284 | D5: =$B5*Model!$H$5*(Model!$H$7*(Assumptions!$B$13*D$4*(1-Assumptions!$B$23)-(Assumptions!$B$21+Assumptions!$B$22))+(1-Model!$H$7)*(Assumptions!$B$5*D$4*(1-Assumptions!$B$23)-Assumptions!$B$21))/1000-Assumptions!$B$25 -> 11.58632 | E5: =$B5*Model!$H$5*(Model!$H$7*(Assumptions!$B$13*E$4*(1-Assumptions!$B$23)-(Assumptions!$B$21+Assumptions!$B$22))+(1-Model!$H$7)*(Assumptions!$B$5*E$4*(1-Assumptions!$B$23)-Assumptions!$B$21))/1000-Assumptions!$B$25 -> 15.1598 | F5: =$B5*Model!$H$5*(Model!$H$7*(Assumptions!$B$13*F$4*(1-Assumptions!$B$23)-(Assumptions!$B$21+Assumptions!$B$22))+(1-Model!$H$7)*(Assumptions!$B$5*F$4*(1-Assumptions!$B$23)-Assumptions!$B$21))/1000-Assumptions!$B$25 -> 18.73328 | G5: =$B5*Model!$H$5*(Model!$H$7*(Assumptions!$B$13*G$4*(1-Assumptions!$B$23)-(Assumptions!$B$21+Assumptions!$B$22))+(1-Model!$H$7)*(Assumptions!$B$5*G$4*(1-Assumptions!$B$23)-Assumptions!$B$21))/1000-Assumptions!$B$25 -> 22.30676
B6: 0.9 | C6: =$B6*Model!$H$5*(Model!$H$7*(Assumptions!$B$13*C$4*(1-Assumptions!$B$23)-(Assumptions!$B$21+Assumptions!$B$22))+(1-Model!$H$7)*(Assumptions!$B$5*C$4*(1-Assumptions!$B$23)-Assumptions!$B$21))/1000-Assumptions!$B$25 -> 10.415408 | D6: =$B6*Model!$H$5*(Model!$H$7*(Assumptions!$B$13*D$4*(1-Assumptions!$B$23)-(Assumptions!$B$21+Assumptions!$B$22))+(1-Model!$H$7)*(Assumptions!$B$5*D$4*(1-Assumptions!$B$23)-Assumptions!$B$21))/1000-Assumptions!$B$25 -> 14.703584 | E6: =$B6*Model!$H$5*(Model!$H$7*(Assumptions!$B$13*E$4*(1-Assumptions!$B$23)-(Assumptions!$B$21+Assumptions!$B$22))+(1-Model!$H$7)*(Assumptions!$B$5*E$4*(1-Assumptions!$B$23)-Assumptions!$B$21))/1000-Assumptions!$B$25 -> 18.99176 | F6: =$B6*Model!$H$5*(Model!$H$7*(Assumptions!$B$13*F$4*(1-Assumptions!$B$23)-(Assumptions!$B$21+Assumptions!$B$22))+(1-Model!$H$7)*(Assumptions!$B$5*F$4*(1-Assumptions!$B$23)-Assumptions!$B$21))/1000-Assumptions!$B$25 -> 23.279936 | G6: =$B6*Model!$H$5*(Model!$H$7*(Assumptions!$B$13*G$4*(1-Assumptions!$B$23)-(Assumptions!$B$21+Assumptions!$B$22))+(1-Model!$H$7)*(Assumptions!$B$5*G$4*(1-Assumptions!$B$23)-Assumptions!$B$21))/1000-Assumptions!$B$25 -> 27.568112
B7: 1 | C7: =$B7*Model!$H$5*(Model!$H$7*(Assumptions!$B$13*C$4*(1-Assumptions!$B$23)-(Assumptions!$B$21+Assumptions!$B$22))+(1-Model!$H$7)*(Assumptions!$B$5*C$4*(1-Assumptions!$B$23)-Assumptions!$B$21))/1000-Assumptions!$B$25 -> 12.01712 | D7: =$B7*Model!$H$5*(Model!$H$7*(Assumptions!$B$13*D$4*(1-Assumptions!$B$23)-(Assumptions!$B$21+Assumptions!$B$22))+(1-Model!$H$7)*(Assumptions!$B$5*D$4*(1-Assumptions!$B$23)-Assumptions!$B$21))/1000-Assumptions!$B$25 -> 16.78176 | E7: =$B7*Model!$H$5*(Model!$H$7*(Assumptions!$B$13*E$4*(1-Assumptions!$B$23)-(Assumptions!$B$21+Assumptions!$B$22))+(1-Model!$H$7)*(Assumptions!$B$5*E$4*(1-Assumptions!$B$23)-Assumptions!$B$21))/1000-Assumptions!$B$25 -> 21.5464 | F7: =$B7*Model!$H$5*(Model!$H$7*(Assumptions!$B$13*F$4*(1-Assumptions!$B$23)-(Assumptions!$B$21+Assumptions!$B$22))+(1-Model!$H$7)*(Assumptions!$B$5*F$4*(1-Assumptions!$B$23)-Assumptions!$B$21))/1000-Assumptions!$B$25 -> 26.31104 | G7: =$B7*Model!$H$5*(Model!$H$7*(Assumptions!$B$13*G$4*(1-Assumptions!$B$23)-(Assumptions!$B$21+Assumptions!$B$22))+(1-Model!$H$7)*(Assumptions!$B$5*G$4*(1-Assumptions!$B$23)-Assumptions!$B$21))/1000-Assumptions!$B$25 -> 31.07568
B8: 1.1 | C8: =$B8*Model!$H$5*(Model!$H$7*(Assumptions!$B$13*C$4*(1-Assumptions!$B$23)-(Assumptions!$B$21+Assumptions!$B$22))+(1-Model!$H$7)*(Assumptions!$B$5*C$4*(1-Assumptions!$B$23)-Assumptions!$B$21))/1000-Assumptions!$B$25 -> 13.618832 | D8: =$B8*Model!$H$5*(Model!$H$7*(Assumptions!$B$13*D$4*(1-Assumptions!$B$23)-(Assumptions!$B$21+Assumptions!$B$22))+(1-Model!$H$7)*(Assumptions!$B$5*D$4*(1-Assumptions!$B$23)-Assumptions!$B$21))/1000-Assumptions!$B$25 -> 18.859936 | E8: =$B8*Model!$H$5*(Model!$H$7*(Assumptions!$B$13*E$4*(1-Assumptions!$B$23)-(Assumptions!$B$21+Assumptions!$B$22))+(1-Model!$H$7)*(Assumptions!$B$5*E$4*(1-Assumptions!$B$23)-Assumptions!$B$21))/1000-Assumptions!$B$25 -> 24.10104 | F8: =$B8*Model!$H$5*(Model!$H$7*(Assumptions!$B$13*F$4*(1-Assumptions!$B$23)-(Assumptions!$B$21+Assumptions!$B$22))+(1-Model!$H$7)*(Assumptions!$B$5*F$4*(1-Assumptions!$B$23)-Assumptions!$B$21))/1000-Assumptions!$B$25 -> 29.342144 | G8: =$B8*Model!$H$5*(Model!$H$7*(Assumptions!$B$13*G$4*(1-Assumptions!$B$23)-(Assumptions!$B$21+Assumptions!$B$22))+(1-Model!$H$7)*(Assumptions!$B$5*G$4*(1-Assumptions!$B$23)-Assumptions!$B$21))/1000-Assumptions!$B$25 -> 34.583248
B9: 1.25 | C9: =$B9*Model!$H$5*(Model!$H$7*(Assumptions!$B$13*C$4*(1-Assumptions!$B$23)-(Assumptions!$B$21+Assumptions!$B$22))+(1-Model!$H$7)*(Assumptions!$B$5*C$4*(1-Assumptions!$B$23)-Assumptions!$B$21))/1000-Assumptions!$B$25 -> 16.0214 | D9: =$B9*Model!$H$5*(Model!$H$7*(Assumptions!$B$13*D$4*(1-Assumptions!$B$23)-(Assumptions!$B$21+Assumptions!$B$22))+(1-Model!$H$7)*(Assumptions!$B$5*D$4*(1-Assumptions!$B$23)-Assumptions!$B$21))/1000-Assumptions!$B$25 -> 21.9772 | E9: =$B9*Model!$H$5*(Model!$H$7*(Assumptions!$B$13*E$4*(1-Assumptions!$B$23)-(Assumptions!$B$21+Assumptions!$B$22))+(1-Model!$H$7)*(Assumptions!$B$5*E$4*(1-Assumptions!$B$23)-Assumptions!$B$21))/1000-Assumptions!$B$25 -> 27.933 | F9: =$B9*Model!$H$5*(Model!$H$7*(Assumptions!$B$13*F$4*(1-Assumptions!$B$23)-(Assumptions!$B$21+Assumptions!$B$22))+(1-Model!$H$7)*(Assumptions!$B$5*F$4*(1-Assumptions!$B$23)-Assumptions!$B$21))/1000-Assumptions!$B$25 -> 33.8888 | G9: =$B9*Model!$H$5*(Model!$H$7*(Assumptions!$B$13*G$4*(1-Assumptions!$B$23)-(Assumptions!$B$21+Assumptions!$B$22))+(1-Model!$H$7)*(Assumptions!$B$5*G$4*(1-Assumptions!$B$23)-Assumptions!$B$21))/1000-Assumptions!$B$25 -> 39.8446

Sheet Bridge & Sources
A1: Capex bridge, V4 to V6 change log, pending confirmations
A3: CAPEX BRIDGE — bottom-up to commitment envelopes (Stages 1+2, USD M)
A4: Bottom-up direct capex, Stages 1+2 (June 2026 build, incl. self-extraction fleet) | B4: 39
A5: Contingency (~12% of direct) | B5: 4.7
A6: Owner's costs, first fills, spares | B6: 2.3
A7: Initial working capital | B7: 4
A8: Total — equals Stage 1 + Stage 2 envelopes | B8: =SUM(B4:B7) -> 50
A9: Ties to the public 25 + 25 = USD 50M. Stage-level split of directs to be firmed with vendor quotes; the previously quoted ~$12M equipment-only figure refers to the plant-equipment subset of directs.
A11: V4 TO V6 CHANGE LOG
A12: 1. Royalty: the $2.00/t unit line (implied 4.4–5.7% ad-valorem) is replaced with the agreed 3.0% ad-valorem (~$1.05–1.35/t at $35–45/t). Decision: June 2026.
A13: 2. Stage 2 pricing: the unsupported $180/t blended figure is replaced with a transparent product-mix stack (Assumptions rows 7–13), anchored to Maluish/VRX guidance and the Market Study band ($40–120/t).
A14: 3. Tax: legacy 30%-of-revenue lines superseded by 10% on profit (2026 industrial rate; legal confirmation pending).
A15: 4. Capex: 25/25 presented as commitment envelopes with a bottom-up bridge (above).
A16: 5. Stage 3 (HPQ): excluded from base-case returns pending metallurgical confirmation; carried as upside only.
A17: 6. The legacy smelter feasibility study is superseded in full; none of its figures are used anywhere in this model.
A20: PENDING CONFIRMATIONS (to close before signing-grade DD)
A21: Syria enacted mining royalty basis (legal)
A22: 10% industrial tax as finalised law (legal)
A23: Stage 2 vendor quotes (acid leach + magnetic separation)
... A29: Estimates and projections reflect the assumptions stated herein and are subject to the pending confirmations above. This model does not constitute an offer of securities. Prepared for evaluation under confidentiality.
